src/__init__.py
src/axion_dmx_api.py
axion_dmx_api-1.0.0.dist-info/LICENSE
axion_dmx_api-1.0.0.dist-info/METADATA
axion_dmx_api-1.0.0.dist-info/WHEEL
axion_dmx_api-1.0.0.dist-info/top_level.txt
axion_dmx_api-1.0.0.dist-info/RECORD
