Metadata-Version: 2.1
Name: axion-dmx-api
Version: 1.0.0
Summary: A Python API for controlling Axion Lighting DMX controllers
Home-page: UNKNOWN
Author: Vrncanac
Author-email: jana13eng@gmail.com
License: UNKNOWN
Platform: UNKNOWN
Classifier: Programming Language :: Python :: 3
Classifier: License :: OSI Approved :: MIT License
Classifier: Operating System :: OS Independent
Requires-Python: >=3.7
